cipher_package/__init__.py
cipher_package/cli.py
cipher_package/cipher_code/aes/client.py
cipher_package/cipher_code/aes/server.py
cipher_package/cipher_code/caesar/client.py
cipher_package/cipher_code/caesar/server.py
cipher_package/cipher_code/des/client.py
cipher_package/cipher_code/des/server.py
cipher_package/cipher_code/hill/client.py
cipher_package/cipher_code/hill/server.py
cipher_package/cipher_code/monoalphabetic/client.py
cipher_package/cipher_code/monoalphabetic/server.py
cipher_package/cipher_code/onetimepad/client.py
cipher_package/cipher_code/onetimepad/server.py
cipher_package/cipher_code/playfair/client.py
cipher_package/cipher_code/playfair/server.py
cipher_package/cipher_code/railfence/client.py
cipher_package/cipher_code/railfence/server.py
cipher_package/cipher_code/rsa/client.py
cipher_package/cipher_code/rsa/server.py
cipher_package/cipher_code/sha/client.py
cipher_package/cipher_code/sha/server.py
cipher_package/cipher_code/vigenere/client.py
cipher_package/cipher_code/vigenere/server.py
cipher_lab-0.1.3.dist-info/LICENSE
cipher_lab-0.1.3.dist-info/METADATA
cipher_lab-0.1.3.dist-info/WHEEL
cipher_lab-0.1.3.dist-info/entry_points.txt
cipher_lab-0.1.3.dist-info/top_level.txt
cipher_lab-0.1.3.dist-info/RECORD
