Metadata-Version: 2.2
Name: cipher-lab
Version: 0.1.3
Summary: Classic cipher implementations with export functionality
Home-page: https://github.com/yourusername/cipher-package
Author: Your Name
Author-email: your@email.com
Keywords: ciphers cryptography encryption decryption
Classifier: Programming Language :: Python :: 3
Classifier: License :: OSI Approved :: MIT License
Classifier: Operating System :: OS Independent
Requires-Python: >=3.6
License-File: LICENSE
Dynamic: author
Dynamic: author-email
Dynamic: classifier
Dynamic: description-content-type
Dynamic: home-page
Dynamic: keywords
Dynamic: requires-python
Dynamic: summary
